hello_pr-0.1.0.dist-info/METADATA
hello_pr-0.1.0.dist-info/WHEEL
hello_pr/__init__.py
hello_pr-0.1.0.dist-info/RECORD
