Metadata-Version: 2.1
Name: hello_PR
Version: 0.1.0
Summary: The Python program I'm distributing for the first time
Author-Email: aaingyunii <dlsrbs98@gmail.com>
License: MIT
Requires-Python: >=3.8
